[
    {
        "model": "cards.card",
        "pk": 1,
        "fields": {
            "is_badge": true,
            "name": "Asuntos Regulatorios",
            "order": 1,
            "true_department": "badge",
            "charge": "IT Guy",
            "birth_date": "1998",
            "description": "badge",
            "photo": "",
            "fk_rarity": 4,
            "fk_department": 1,
            "wave": 1,
            "active": true,
            "arrival_date": "2018",
            "page": 1
        }
    },
    {
        "model": "cards.card",
        "pk": 2,
        "fields": {
            "is_badge": false,
            "name": "María del Carmen Velázquez",
            "order": 2,
            "description": "Se considera perseverante, alguien que no se rinde, cumple lo que se propone y es muy insistente.",
            "true_department": "Ventas",
            "charge": "IBM",
            "birth_date": "7 octubre",
            "photo": "",
            "fk_rarity": 2,
            "fk_department": 1,
            "wave": 1,
            "active": true,
            "arrival_date": "2015",
            "page": 1
        }
    },
    {
        "model": "cards.card",
        "pk": 3,
        "fields": {
            "is_badge": true,
            "name": "Bonus",
            "order": 1,
            "true_department": "badge",
            "charge": "IT Guy",
            "birth_date": "1998",
            "description": "badge",
            "photo": "",
            "fk_rarity": 4,
            "fk_department": 2,
            "wave": 1,
            "active": true,
            "arrival_date": "2018",
            "page": 1
        }
    },
    {
        "model": "cards.card",
        "pk": 4,
        "fields": {
            "is_badge": false,
            "name": "María del Carmen Velázquez",
            "order": 2,
            "description": "Se considera perseverante, alguien que no se rinde, cumple lo que se propone y es muy insistente.",
            "true_department": "Ventas",
            "charge": "IBM",
            "birth_date": "7 octubre",
            "photo": "",
            "fk_rarity": 2,
            "fk_department": 2,
            "wave": 1,
            "active": true,
            "arrival_date": "2015",
            "page": 1
        }
    },
    {
        "model": "cards.card",
        "pk": 5,
        "fields": {
            "is_badge": true,
            "name": "Calidad y Cumplimiento",
            "order": 1,
            "true_department": "badge",
            "charge": "IT Guy",
            "birth_date": "1998",
            "description": "badge",
            "photo": "",
            "fk_rarity": 4,
            "fk_department": 3,
            "wave": 1,
            "active": true,
            "arrival_date": "2018",
            "page": 1
        }
    },
    {
        "model": "cards.card",
        "pk": 6,
        "fields": {
            "is_badge": false,
            "name": "María del Carmen Velázquez",
            "order": 2,
            "description": "Se considera perseverante, alguien que no se rinde, cumple lo que se propone y es muy insistente.",
            "true_department": "Ventas",
            "charge": "IBM",
            "birth_date": "7 octubre",
            "photo": "",
            "fk_rarity": 2,
            "fk_department": 3,
            "wave": 1,
            "active": true,
            "arrival_date": "2015",
            "page": 1
        }
    },
    {
        "model": "cards.card",
        "pk": 7,
        "fields": {
            "is_badge": true,
            "name": "Contabilidad y finanzas",
            "order": 1,
            "true_department": "badge",
            "charge": "IT Guy",
            "birth_date": "1998",
            "description": "badge",
            "photo": "",
            "fk_rarity": 4,
            "fk_department": 4,
            "wave": 1,
            "active": true,
            "arrival_date": "2018",
            "page": 1
        }
    },
    {
        "model": "cards.card",
        "pk": 8,
        "fields": {
            "is_badge": false,
            "name": "María del Carmen Velázquez",
            "order": 2,
            "description": "Se considera perseverante, alguien que no se rinde, cumple lo que se propone y es muy insistente.",
            "true_department": "Ventas",
            "charge": "IBM",
            "birth_date": "7 octubre",
            "photo": "",
            "fk_rarity": 2,
            "fk_department": 4,
            "wave": 1,
            "active": true,
            "arrival_date": "2015",
            "page": 1
        }
    },
    {
        "model": "cards.card",
        "pk": 9,
        "fields": {
            "is_badge": true,
            "name": "Gerencias y Direcciones",
            "order": 1,
            "true_department": "badge",
            "charge": "IT Guy",
            "birth_date": "1998",
            "description": "badge",
            "photo": "",
            "fk_rarity": 4,
            "fk_department": 5,
            "wave": 1,
            "active": true,
            "arrival_date": "2018",
            "page": 1
        }
    },
    {
        "model": "cards.card",
        "pk": 10,
        "fields": {
            "is_badge": false,
            "name": "María del Carmen Velázquez",
            "order": 2,
            "description": "Se considera perseverante, alguien que no se rinde, cumple lo que se propone y es muy insistente.",
            "true_department": "Ventas",
            "charge": "IBM",
            "birth_date": "7 octubre",
            "photo": "",
            "fk_rarity": 2,
            "fk_department": 5,
            "wave": 1,
            "active": true,
            "arrival_date": "2015",
            "page": 1
        }
    },
    {
        "model": "cards.card",
        "pk": 11,
        "fields": {
            "is_badge": true,
            "name": "Importaciones",
            "order": 1,
            "true_department": "badge",
            "charge": "IT Guy",
            "birth_date": "1998",
            "description": "badge",
            "photo": "",
            "fk_rarity": 4,
            "fk_department": 6,
            "wave": 1,
            "active": true,
            "arrival_date": "2018",
            "page": 1
        }
    },
    {
        "model": "cards.card",
        "pk": 12,
        "fields": {
            "is_badge": false,
            "name": "María del Carmen Velázquez",
            "order": 2,
            "description": "Se considera perseverante, alguien que no se rinde, cumple lo que se propone y es muy insistente.",
            "true_department": "Ventas",
            "charge": "IBM",
            "birth_date": "7 octubre",
            "photo": "",
            "fk_rarity": 2,
            "fk_department": 6,
            "wave": 1,
            "active": true,
            "arrival_date": "2015",
            "page": 1
        }
    },
    {
        "model": "cards.card",
        "pk": 13,
        "fields": {
            "is_badge": true,
            "name": "Logística",
            "order": 1,
            "true_department": "badge",
            "charge": "IT Guy",
            "birth_date": "1998",
            "description": "badge",
            "photo": "",
            "fk_rarity": 4,
            "fk_department": 1,
            "wave": 1,
            "active": true,
            "arrival_date": "2018",
            "page": 1
        }
    },
    {
        "model": "cards.card",
        "pk": 14,
        "fields": {
            "is_badge": false,
            "name": "María del Carmen Velázquez",
            "order": 2,
            "description": "Se considera perseverante, alguien que no se rinde, cumple lo que se propone y es muy insistente.",
            "true_department": "Ventas",
            "charge": "IBM",
            "birth_date": "7 octubre",
            "photo": "",
            "fk_rarity": 2,
            "fk_department": 7,
            "wave": 1,
            "active": true,
            "arrival_date": "2015",
            "page": 1
        }
    },
    {
        "model": "cards.card",
        "pk": 15,
        "fields": {
            "is_badge": true,
            "name": "Mantenimiento",
            "order": 1,
            "true_department": "badge",
            "charge": "IT Guy",
            "birth_date": "1998",
            "description": "badge",
            "photo": "",
            "fk_rarity": 4,
            "fk_department": 8,
            "wave": 1,
            "active": true,
            "arrival_date": "2018",
            "page": 1
        }
    },
    {
        "model": "cards.card",
        "pk": 16,
        "fields": {
            "is_badge": false,
            "name": "María del Carmen Velázquez",
            "order": 2,
            "description": "Se considera perseverante, alguien que no se rinde, cumple lo que se propone y es muy insistente.",
            "true_department": "Ventas",
            "charge": "IBM",
            "birth_date": "7 octubre",
            "photo": "",
            "fk_rarity": 2,
            "fk_department": 8,
            "wave": 1,
            "active": true,
            "arrival_date": "2015",
            "page": 1
        }
    },
    {
        "model": "cards.card",
        "pk": 17,
        "fields": {
            "is_badge": true,
            "name": "Operaciones",
            "order": 1,
            "true_department": "badge",
            "charge": "IT Guy",
            "birth_date": "1998",
            "description": "badge",
            "photo": "",
            "fk_rarity": 4,
            "fk_department": 9,
            "wave": 1,
            "active": true,
            "arrival_date": "2018",
            "page": 1
        }
    },
    {
        "model": "cards.card",
        "pk": 18,
        "fields": {
            "is_badge": false,
            "name": "María del Carmen Velázquez",
            "order": 2,
            "description": "Se considera perseverante, alguien que no se rinde, cumple lo que se propone y es muy insistente.",
            "true_department": "Ventas",
            "charge": "IBM",
            "birth_date": "7 octubre",
            "photo": "",
            "fk_rarity": 2,
            "fk_department": 9,
            "wave": 1,
            "active": true,
            "arrival_date": "2015",
            "page": 1
        }
    },
    {
        "model": "cards.card",
        "pk": 19,
        "fields": {
            "is_badge": true,
            "name": "Recursos Humanos",
            "order": 1,
            "true_department": "badge",
            "charge": "IT Guy",
            "birth_date": "1998",
            "description": "badge",
            "photo": "",
            "fk_rarity": 4,
            "fk_department": 10,
            "wave": 1,
            "active": true,
            "arrival_date": "2018",
            "page": 1
        }
    },
    {
        "model": "cards.card",
        "pk": 20,
        "fields": {
            "is_badge": false,
            "name": "María del Carmen Velázquez",
            "order": 2,
            "description": "Se considera perseverante, alguien que no se rinde, cumple lo que se propone y es muy insistente.",
            "true_department": "Ventas",
            "charge": "IBM",
            "birth_date": "7 octubre",
            "photo": "",
            "fk_rarity": 2,
            "fk_department": 10,
            "wave": 1,
            "active": true,
            "arrival_date": "2015",
            "page": 1
        }
    },
    {
        "model": "cards.card",
        "pk": 21,
        "fields": {
            "is_badge": true,
            "name": "Soporte Técnico",
            "order": 1,
            "true_department": "badge",
            "charge": "IT Guy",
            "birth_date": "1998",
            "description": "badge",
            "photo": "",
            "fk_rarity": 4,
            "fk_department": 11,
            "wave": 1,
            "active": true,
            "arrival_date": "2018",
            "page": 1
        }
    },
    {
        "model": "cards.card",
        "pk": 22,
        "fields": {
            "is_badge": false,
            "name": "María del Carmen Velázquez",
            "order": 2,
            "description": "Se considera perseverante, alguien que no se rinde, cumple lo que se propone y es muy insistente.",
            "true_department": "Ventas",
            "charge": "IBM",
            "birth_date": "7 octubre",
            "photo": "",
            "fk_rarity": 2,
            "fk_department": 11,
            "wave": 1,
            "active": true,
            "arrival_date": "2015",
            "page": 1
        }
    },
    {
        "model": "cards.card",
        "pk": 22,
        "fields": {
            "is_badge": true,
            "name": "Ventas",
            "order": 1,
            "true_department": "badge",
            "charge": "IT Guy",
            "birth_date": "1998",
            "description": "badge",
            "photo": "",
            "fk_rarity": 4,
            "fk_department": 12,
            "wave": 1,
            "active": true,
            "arrival_date": "2018",
            "page": 1
        }
    },
    {
        "model": "cards.card",
        "pk": 24,
        "fields": {
            "is_badge": false,
            "name": "María del Carmen Velázquez",
            "order": 2,
            "description": "Se considera perseverante, alguien que no se rinde,\ncumple lo que se propone y es muy insistente.",
            "true_department": "Ventas",
            "charge": "IBM",
            "birth_date": "7 octubre",
            "photo": "",
            "fk_rarity": 2,
            "fk_department": 12,
            "wave": 1,
            "active": true,
            "arrival_date": "2015",
            "page": 1
        }
    }
]